noop.cpython-311-darwin.so
sqlite_vss/__init__.py
sqlite_vss/vector0.dylib
sqlite_vss/version.py
sqlite_vss/vss0.dylib
sqlite_vss-0.1.2.dist-info/METADATA
sqlite_vss-0.1.2.dist-info/WHEEL
sqlite_vss-0.1.2.dist-info/top_level.txt
sqlite_vss-0.1.2.dist-info/RECORD
