Metadata-Version: 2.1
Name: sqlite-vss
Version: 0.1.2
Home-page: https://github.com/asg017/sqlite-vss
Author: Alex Garcia
License: MIT License, Apache License, Version 2.0
Project-URL: Issues, https://github.com/asg017/sqlite-vss/issues
Project-URL: CI, https://github.com/asg017/sqlite-vss/actions
Project-URL: Changelog, https://github.com/asg017/sqlite-vss/releases
Requires-Python: >=3.7
Provides-Extra: test
Requires-Dist: pytest ; extra == 'test'
